{
    "cloudsObj":[
        {
            "path":"assets/cloud1.png",
            "width":2,
            "height":5,
            "posX":500,
            "posY":3,
            "speed":2
        },
        {
            "path":"assets/cloud2.png",
            "width":3,
            "height":6,
            "posX":100,
            "posY":4,
            "speed":1
        },
        {
            "path":"assets/cloud3.png",
            "width":4,
            "height":7,
            "posX":800,
            "posY":5,
            "speed":0.5
        },
        {
            "path":"assets/cloud4.png",
            "width":5,
            "height":8,
            "posX":210,
            "posY":6,
            "speed":3
        }
    ],
    
    "cactus":[
        {
            "path":"assets/cactus1.png",
            "width":20,
            "height":5
        },
        {
            "path":"assets/cactus2.png",
            "width":25,
            "height":5
        },
        {
            "path":"assets/cactus3.png",
            "width":30,
            "height":5
        }
    ],

    "stickman":{
        "posX":100,
        "posY":100,
        "width":50,
        "height":100,
        "fast":[
            {
                "path":"assets/fast/1.png"
            },{
                "path":"assets/fast/2.png"
            },{
                "path":"assets/fast/3.png"
            },{
                "path":"assets/fast/4.png"
            },{
                "path":"assets/fast/5.png"
            },{
                "path":"assets/fast/6.png"
            }
        ]
    }
}